odoo/addons/partner_contact_birthplace/README.rst
odoo/addons/partner_contact_birthplace/__init__.py
odoo/addons/partner_contact_birthplace/__manifest__.py
odoo/addons/partner_contact_birthplace/i18n/it.po
odoo/addons/partner_contact_birthplace/i18n/partner_contact_birthplace.pot
odoo/addons/partner_contact_birthplace/models/__init__.py
odoo/addons/partner_contact_birthplace/models/res_partner.py
odoo/addons/partner_contact_birthplace/static/description/icon.png
odoo/addons/partner_contact_birthplace/views/res_partner.xml
odoo12_addon_partner_contact_birthplace-12.0.1.0.0.99.dev5.dist-info/METADATA
odoo12_addon_partner_contact_birthplace-12.0.1.0.0.99.dev5.dist-info/WHEEL
odoo12_addon_partner_contact_birthplace-12.0.1.0.0.99.dev5.dist-info/top_level.txt
odoo12_addon_partner_contact_birthplace-12.0.1.0.0.99.dev5.dist-info/RECORD
