Metadata-Version: 2.1
Name: odoo12-addon-partner-contact-birthplace
Version: 12.0.1.0.0.99.dev5
Summary: This module allows to define a birthplace for partners.
Home-page: https://github.com/OCA/partner-contactpartner_contact_birthplace
Author: Agile Business Group, Odoo Community Association (OCA)
Author-email: support@odoo-community.org
License: AGPL-3
Platform: UNKNOWN
Classifier: Programming Language :: Python
Classifier: Framework :: Odoo
Classifier: Framework :: Odoo :: 12.0
Classifier: License :: OSI Approved :: GNU Affero General Public License v3
Requires-Python: >=3.5
Requires-Dist: odoo12-addon-partner-contact-personal-information-page
Requires-Dist: odoo (<12.1dev,>=12.0a)
